{
  // ====== BLOCO (Blocos) ======
  "parede": "wall",
  "parede_grande": "large-wall",
  "parede_titanio": "titanium-wall",
  "parede_plastanio": "plastanium-wall",
  "defesa": "defense",
  "fabrica": "factory",
  "fabrica_plasma": "plasma-factory",
  "fundidor_liga": "alloy-smelter",
  "construtor": "constructor",
  "reparador": "mender",
  "projetor_reparo": "mend-projector",
  "torre": "turret",
  "duo": "duo",
  "lançador": "lancer",
  "salva": "salvo",
  "onda": "wave",
  "ripple": "ripple",
  "fusão": "fuse",
  "gerador": "power-generator",
  "gerador_termico": "thermal-generator",
  "painel_solar": "solar-panel",
  "painel_solar_grande": "large-solar-panel",
  "reator_torio": "thorium-reactor",
  "bomba_mecanica": "mechanical-pump",
  "bomba_rotativa": "rotary-pump",
  "processador": "processor",
  "micro_processador": "micro-processor",
  "hiper_processador": "hyper-processor",

  // ====== ITEM (Itens) ======
  "cobre": "copper",
  "chumbo": "lead",
  "carvão": "coal",
  "titanio": "titanium",
  "torio": "thorium",
  "silicio": "silicon",
  "vidro_metalico": "metaglass",
  "liga_de_choque": "surge-alloy",
  "tecido_de_fase": "phase-fabric",
  "plastanio": "plastanium",
  "areia": "sand",
  "pedra": "stone",
  "gelo": "ice",
  "fundidor": "melter",

  // ====== LIQUIDO (Líquidos) ======
  "agua": "water",
  "oleo": "oil",
  "criofluido": "cryofluid",
  "escoria": "slag",

  // ====== UNIDADE (Unidades) ======
  "flare": "flare",
  "mono": "mono",
  "poli": "poly",
  "mega": "mega",
  "zenite": "zenith",
  "antumbra": "antumbra",
  "quasar": "quasar",
  "adaga": "dagger",
  "titan": "titan",
  "fortaleza": "fortress",
  "nova": "nova",
  "pulsar": "pulsar",
  "quark": "quark",
  "rastreador": "crawler",

  // ====== COMANDO (Comandos) ======
  "minerar": "mine",
  "construir": "build",
  "remover": "remove",
  "entregar": "deliver",
  "comando": "command",
  "impulsionar": "boost",
  "reparar": "repair",
  "defender": "defend",
  "atacar": "attack",
  "rota": "path",
  "esperar": "wait",
  "calcular": "calc",

  // ====== ESTATISTICA (Status) ======
  "energia": "power",
  "força": "strength",
  "velocidade": "speed",
  "eficiencia": "efficiency",
  "capacidade": "capacity",
  "fluxo": "flow",
  "custo": "cost",
  "reparo": "repair",
  "saude": "health",
  "overdrive": "overdrive",
  "finalizar": "finish",
  "ativo": "active",
  "desativar": "disable",

  // ====== SISTEMA (Sistema) ======
  "projeto": "project",
  "logica": "logic",
  "codigo": "code",
  "celula": "cell",
  "planeta": "planet",
  "mundo": "world",
  "setor": "sector",
  "minerio": "ore",
  "solo": "ground",
  "base": "base",
  "escudo": "shield",
  "nucleo": "core",
  "nucleo_fragmento": "core-shard",
  "nucleo_fundacao": "core-foundation",
  "nucleo_nucleo": "core-nucleus"
}
